podmanclispawner/__init__.py
podmanclispawner/podmanspawner.py
podmanclispawner-0.3.0.dist-info/LICENSE
podmanclispawner-0.3.0.dist-info/METADATA
podmanclispawner-0.3.0.dist-info/WHEEL
podmanclispawner-0.3.0.dist-info/entry_points.txt
podmanclispawner-0.3.0.dist-info/top_level.txt
podmanclispawner-0.3.0.dist-info/RECORD
