Metadata-Version: 2.1
Name: podmanclispawner
Version: 0.3.0
Summary: PodmanCLISpawner for JupyterHub
Author: Simon Li, Niklas Netter
License: BSD
Project-URL: Homepage, https://github.com/manics/podmanclispawner
Project-URL: Source, https://github.com/manics/podmanclispawner
Project-URL: Tracker, https://github.com/manics/podmanclispawner/issues
Keywords: jupyterhub,spawner
Classifier: Framework :: Jupyter
Classifier: Intended Audience :: Developers
Classifier: Intended Audience :: System Administrators
Classifier: Intended Audience :: Science/Research
Classifier: License :: OSI Approved :: BSD License
Classifier: Programming Language :: Python
Classifier: Programming Language :: Python :: 3
Requires-Python: >=3.7
License-File: LICENSE
Requires-Dist: jupyterhub >=4
Requires-Dist: traitlets >=5
